pyvdl/__init__.py
pyvdl/fast.py
pyvdl/libs.py
pyvdl/other.py
pyvdl-0.0.5.dist-info/LICENSE
pyvdl-0.0.5.dist-info/METADATA
pyvdl-0.0.5.dist-info/WHEEL
pyvdl-0.0.5.dist-info/top_level.txt
pyvdl-0.0.5.dist-info/RECORD
