Metadata-Version: 2.1
Name: pyvdl
Version: 0.0.5
Summary: vectors draw lib, update: add fast render & Refactor code
Author-email: Kolya142 <trim.fears_0k@icloud.com>
License: MIT License        
Project-URL: Homepage, https://github.com/Kolya142/vectors-draw-lib
Project-URL: Bug Tracker, https://github.com/Kolya142/vectors-draw-lib/issues
Classifier: Programming Language :: Python :: 3
Classifier: License :: OSI Approved :: MIT License
Classifier: Operating System :: OS Independent
Requires-Python: >=3.7
License-File: LICENSE
